pyonix/__init__.py
pyonix/client.py
pyonix/models.py
pyonix/endpoints/__init__.py
pyonix/endpoints/action_items.py
pyonix/endpoints/assessments.py
pyonix/endpoints/connections.py
pyonix/endpoints/dashboards.py
pyonix/endpoints/tags.py
pyonix-0.1.3.dist-info/METADATA
pyonix-0.1.3.dist-info/WHEEL
pyonix-0.1.3.dist-info/top_level.txt
pyonix-0.1.3.dist-info/RECORD
