Metadata-Version: 2.1
Name: pyonix
Version: 0.1.3
Summary: A Python client library for the Ionix API
Author: Josiah
Classifier: Development Status :: 3 - Alpha
Classifier: Intended Audience :: Developers
Classifier: License :: OSI Approved :: MIT License
Classifier: Programming Language :: Python :: 3
Classifier: Programming Language :: Python :: 3.7
Classifier: Programming Language :: Python :: 3.8
Classifier: Programming Language :: Python :: 3.9
Classifier: Programming Language :: Python :: 3.10
Classifier: Programming Language :: Python :: 3.11
Classifier: Programming Language :: Python :: 3.12
Requires-Python: >=3.7
Requires-Dist: aiohttp>=3.11.4
Requires-Dist: requests>=2.32.3
Provides-Extra: test
Requires-Dist: unittest-mock>=1.3.0; extra == "test"
